{
  "PresetList": [
    {
      "ChildrenArray": [
        {
          "AlignAVStart": true,
          "AudioCopyMask": [
            "copy:aac"
          ],
          "AudioEncoderFallback": "av_aac",
          "AudioLanguageList": [],
          "AudioList": [
            {
              "AudioBitrate": 64,
              "AudioCompressionLevel": 0,
              "AudioEncoder": "av_aac",
              "AudioMixdown": "stereo",
              "AudioNormalizeMixLevel": false,
              "AudioSamplerate": "8",
              "AudioTrackQualityEnable": false,
              "AudioTrackQuality": -1,
              "AudioTrackGainSlider": 0,
              "AudioTrackDRCSlider": 0
            }
          ],
          "AudioSecondaryEncoderMode": true,
          "AudioTrackSelectionBehavior": "first",
          "ChapterMarkers": true,
          "ChildrenArray": [],
          "Default": false,
          "FileFormat": "av_mp4",
          "Folder": false,
          "FolderOpen": false,
          "Mp4HttpOptimize": true,
          "Mp4iPodCompatible": true,
          "PictureCropMode": 0,
          "PictureBottomCrop": 0,
          "PictureLeftCrop": 0,
          "PictureRightCrop": 0,
          "PictureTopCrop": 0,
          "PictureDARWidth": 0,
          "PictureDeblockPreset": "ultralight",
          "PictureDeblockTune": "large",
          "PictureDeblockCustom": "",
          "PictureDeinterlaceFilter": "off",
          "PictureCombDetectPreset": "off",
          "PictureCombDetectCustom": "",
          "PictureDenoiseCustom": "",
          "PictureDenoiseFilter": "nlmeans",
          "PictureDenoisePreset": "ultralight",
          "PictureDenoiseTune": "none",
          "PictureSharpenCustom": "",
          "PictureSharpenFilter": "unsharp",
          "PictureSharpenPreset": "ultralight",
          "PictureSharpenTune": "ultrafine",
          "PictureDetelecine": "off",
          "PictureDetelecineCustom": "",
          "PictureColorspacePreset": "off",
          "PictureColorspaceCustom": "",
          "PictureChromaSmoothPreset": "ultralight",
          "PictureChromaSmoothTune": "wide",
          "PictureChromaSmoothCustom": "",
          "PictureItuPAR": false,
          "PictureKeepRatio": true,
          "PicturePAR": "auto",
          "PicturePARWidth": 0,
          "PicturePARHeight": 0,
          "PictureWidth": 182,
          "PictureHeight": 102,
          "PictureUseMaximumSize": false,
          "PictureAllowUpscaling": false,
          "PictureForceHeight": 0,
          "PictureForceWidth": 0,
          "PicturePadMode": "none",
          "PicturePadTop": 0,
          "PicturePadBottom": 0,
          "PicturePadLeft": 0,
          "PicturePadRight": 0,
          "PresetName": "SHIT QUALITY",
          "Type": 1,
          "SubtitleAddCC": false,
          "SubtitleAddForeignAudioSearch": true,
          "SubtitleAddForeignAudioSubtitle": false,
          "SubtitleBurnBehavior": "foreign",
          "SubtitleBurnBDSub": false,
          "SubtitleBurnDVDSub": false,
          "SubtitleLanguageList": [],
          "SubtitleTrackSelectionBehavior": "none",
          "VideoAvgBitrate": 0,
          "VideoColorMatrixCode": 0,
          "VideoEncoder": "x264",
          "VideoFramerate": "5",
          "VideoFramerateMode": "pfr",
          "VideoGrayScale": false,
          "VideoScaler": "swscale",
          "VideoPreset": "fast",
          "VideoTune": "",
          "VideoProfile": "auto",
          "VideoLevel": "auto",
          "VideoOptionExtra": "",
          "VideoQualityType": 2,
          "VideoQualitySlider": 47.5,
          "VideoTwoPass": false,
          "VideoTurboTwoPass": false,
          "x264UseAdvancedOptions": false,
          "PresetDisabled": false,
          "MetadataPassthrough": true
        },
        {
          "AlignAVStart": true,
          "AudioCopyMask": [
            "copy:aac"
          ],
          "AudioEncoderFallback": "av_aac",
          "AudioLanguageList": [],
          "AudioList": [
            {
              "AudioBitrate": 160,
              "AudioCompressionLevel": 0,
              "AudioEncoder": "av_aac",
              "AudioMixdown": "stereo",
              "AudioNormalizeMixLevel": false,
              "AudioSamplerate": "auto",
              "AudioTrackQualityEnable": false,
              "AudioTrackQuality": -1,
              "AudioTrackGainSlider": 0,
              "AudioTrackDRCSlider": 0
            }
          ],
          "AudioSecondaryEncoderMode": true,
          "AudioTrackSelectionBehavior": "first",
          "ChapterMarkers": true,
          "ChildrenArray": [],
          "Default": false,
          "FileFormat": "av_mp4",
          "Folder": false,
          "FolderOpen": false,
          "Mp4HttpOptimize": false,
          "Mp4iPodCompatible": false,
          "PictureCropMode": 0,
          "PictureBottomCrop": 0,
          "PictureLeftCrop": 0,
          "PictureRightCrop": 0,
          "PictureTopCrop": 0,
          "PictureDARWidth": 0,
          "PictureDeblockPreset": "off",
          "PictureDeblockTune": "medium",
          "PictureDeblockCustom": "strength=strong:thresh=20:blocksize=8",
          "PictureDeinterlaceFilter": "decomb",
          "PictureCombDetectPreset": "default",
          "PictureCombDetectCustom": "",
          "PictureDeinterlacePreset": "default",
          "PictureDeinterlaceCustom": "",
          "PictureDenoiseCustom": "",
          "PictureDenoiseFilter": "nlmeans",
          "PictureDenoisePreset": "ultralight",
          "PictureDenoiseTune": "none",
          "PictureSharpenCustom": "",
          "PictureSharpenFilter": "unsharp",
          "PictureSharpenPreset": "ultralight",
          "PictureSharpenTune": "fine",
          "PictureDetelecine": "off",
          "PictureDetelecineCustom": "",
          "PictureColorspacePreset": "off",
          "PictureColorspaceCustom": "",
          "PictureChromaSmoothPreset": "ultralight",
          "PictureChromaSmoothTune": "verywide",
          "PictureChromaSmoothCustom": "",
          "PictureItuPAR": false,
          "PictureKeepRatio": true,
          "PicturePAR": "auto",
          "PicturePARWidth": 0,
          "PicturePARHeight": 0,
          "PictureWidth": 720,
          "PictureHeight": 480,
          "PictureUseMaximumSize": false,
          "PictureAllowUpscaling": false,
          "PictureForceHeight": 0,
          "PictureForceWidth": 0,
          "PicturePadMode": "none",
          "PicturePadTop": 0,
          "PicturePadBottom": 0,
          "PicturePadLeft": 0,
          "PicturePadRight": 0,
          "PresetName": "VHS Downsample",
          "Type": 1,
          "SubtitleAddCC": false,
          "SubtitleAddForeignAudioSearch": true,
          "SubtitleAddForeignAudioSubtitle": false,
          "SubtitleBurnBehavior": "foreign",
          "SubtitleBurnBDSub": false,
          "SubtitleBurnDVDSub": false,
          "SubtitleLanguageList": [],
          "SubtitleTrackSelectionBehavior": "none",
          "VideoAvgBitrate": 0,
          "VideoColorMatrixCode": 0,
          "VideoEncoder": "x264",
          "VideoFramerateMode": "vfr",
          "VideoGrayScale": false,
          "VideoScaler": "swscale",
          "VideoPreset": "veryfast",
          "VideoTune": "",
          "VideoProfile": "main",
          "VideoLevel": "4.0",
          "VideoOptionExtra": "",
          "VideoQualityType": 2,
          "VideoQualitySlider": 26.5,
          "VideoTwoPass": true,
          "VideoTurboTwoPass": true,
          "x264UseAdvancedOptions": false,
          "PresetDisabled": false,
          "MetadataPassthrough": true
        }
      ],
      "Folder": true,
      "PresetName": "Custom Presets",
      "PresetDescription": "",
      "Type": 0
    }
  ],
  "VersionMajor": 50,
  "VersionMicro": 0,
  "VersionMinor": 0
}